[
    {
        "props": {
            "autoFocus": false,
            "columnWidth": "md",
            "conditions": null,
            "dependsOnAny": false,
            "dependsOnKeys": null,
            "disabled": false,
            "editablePrefill": false,
            "helperText": null,
            "label": "Plan",
            "name": "plan",
            "options": [
                {
                    "data": null,
                    "label": "Free",
                    "value": "free"
                },
                {
                    "data": null,
                    "label": "Pro",
                    "value": "pro"
                },
                {
                    "data": null,
                    "label": "Enterprise",
                    "value": "enterprise"
                }
            ],
            "prefillRefreshOn": null,
            "prefillResetOn": null,
            "readOnly": false,
            "required": false,
            "tabIndex": null,
            "tooltip": null,
            "value": null
        },
        "type": "field.choice"
    }
]
