[
    {
        "props": {
            "autoComplete": null,
            "autoFocus": null,
            "conditions": null,
            "confirmation": {
                "label": "Confirm password",
                "name": "password_confirmation",
                "placeholder": "Confirm password"
            },
            "dependsOnAny": null,
            "dependsOnKeys": null,
            "disabled": null,
            "helperText": null,
            "hidden": null,
            "label": "Password",
            "labelAction": null,
            "name": "password",
            "passwordRules": null,
            "placeholder": null,
            "readOnly": null,
            "required": null,
            "tabIndex": null,
            "value": null
        },
        "type": "form.password-input"
    }
]
