[
    {
        "props": {
            "addLabel": "Add line",
            "columnWidth": "md",
            "conditions": null,
            "defaultItems": 1,
            "dependsOnAny": false,
            "dependsOnKeys": null,
            "disabled": false,
            "editablePrefill": false,
            "helperText": null,
            "itemLabel": null,
            "label": "Line items",
            "layout": "stack",
            "maxItems": 5,
            "minItems": 1,
            "name": "items",
            "prefillRefreshOn": null,
            "prefillResetOn": null,
            "readOnly": false,
            "reorderable": true,
            "required": false,
            "resizableColumns": false,
            "resizeIndicator": false,
            "rowActions": null,
            "tooltip": null,
            "value": null
        },
        "schema": [
            {
                "props": {
                    "autoComplete": null,
                    "autoFocus": false,
                    "columnWidth": "md",
                    "conditions": null,
                    "copyable": false,
                    "dependsOnAny": false,
                    "dependsOnKeys": null,
                    "disabled": false,
                    "editablePrefill": false,
                    "helperText": null,
                    "label": "Name",
                    "name": "name",
                    "placeholder": null,
                    "prefillRefreshOn": null,
                    "prefillResetOn": null,
                    "prefix": null,
                    "readOnly": false,
                    "required": true,
                    "suffix": null,
                    "tabIndex": null,
                    "tooltip": null,
                    "type": null,
                    "value": null
                },
                "type": "field.text-input"
            },
            {
                "props": {
                    "autoComplete": null,
                    "autoFocus": false,
                    "columnWidth": "md",
                    "conditions": null,
                    "copyable": false,
                    "dependsOnAny": false,
                    "dependsOnKeys": null,
                    "disabled": false,
                    "editablePrefill": false,
                    "helperText": null,
                    "label": "Qty",
                    "name": "qty",
                    "placeholder": null,
                    "prefillRefreshOn": null,
                    "prefillResetOn": null,
                    "prefix": null,
                    "readOnly": false,
                    "required": false,
                    "suffix": null,
                    "tabIndex": null,
                    "tooltip": null,
                    "type": null,
                    "value": null
                },
                "type": "field.text-input"
            }
        ],
        "type": "field.repeater"
    }
]
