[
    {
        "id": "invoices",
        "props": {
            "actionsLabel": "Actions",
            "bulkActions": [],
            "columns": [
                {
                    "key": "number",
                    "props": {
                        "align": "start",
                        "badge": null,
                        "copyable": false,
                        "date": null,
                        "filter": null,
                        "hiddenByDefault": false,
                        "label": "Invoice",
                        "link": null,
                        "multiple": null,
                        "sortable": false,
                        "toggleable": false,
                        "width": "md"
                    },
                    "type": "column.text"
                },
                {
                    "key": "total",
                    "props": {
                        "align": "end",
                        "copyable": false,
                        "currency": "EUR",
                        "currencyField": null,
                        "filter": null,
                        "hiddenByDefault": false,
                        "label": "Total",
                        "maximumFractionDigits": null,
                        "minimumFractionDigits": null,
                        "sortable": true,
                        "toggleable": false,
                        "width": "md"
                    },
                    "type": "column.money"
                },
                {
                    "key": "refunded",
                    "props": {
                        "align": "end",
                        "copyable": false,
                        "currency": null,
                        "currencyField": "currency",
                        "filter": null,
                        "hiddenByDefault": false,
                        "label": "Refunded",
                        "maximumFractionDigits": null,
                        "minimumFractionDigits": null,
                        "sortable": false,
                        "toggleable": false,
                        "width": "md"
                    },
                    "type": "column.money"
                }
            ],
            "data": [
                {
                    "currency": "USD",
                    "number": "INV-1001",
                    "refunded": "0.00",
                    "total": "189.00"
                },
                {
                    "currency": "GBP",
                    "number": "INV-1002",
                    "refunded": "49.50",
                    "total": "49.50"
                }
            ],
            "emptyLabel": "No results",
            "endpoint": null,
            "filters": [],
            "layout": null,
            "lazy": false,
            "pagination": {
                "currentPage": null,
                "from": 1,
                "hasMore": false,
                "lastPage": null,
                "mode": "none",
                "nextPage": null,
                "perPage": null,
                "to": 2,
                "total": 2
            },
            "query": {
                "filters": [],
                "page": 1,
                "perPage": 25,
                "sorts": [],
                "tableFilterIndicators": [],
                "tableFilters": {}
            },
            "resizableColumns": false,
            "resizeIndicator": false,
            "striped": false
        },
        "type": "table"
    }
]
